neighborhoodize/__init__.py
neighborhoodize/city_of_chicago.py
neighborhoodize/common.py
neighborhoodize/constants.py
neighborhoodize/kml_parsers.py
neighborhoodize/nyc.py
neighborhoodize/zillow.py
neighborhoodize/data/.DS_Store
neighborhoodize/data/__init__.py
neighborhoodize/data/__pycache__/__init__.cpython-37.pyc
neighborhoodize/data/city_of_chicago/Boundaries - Community Areas (current).kml
neighborhoodize/data/city_of_chicago/Boundaries - Neighborhoods.kml
neighborhoodize/data/nyc/.DS_Store
neighborhoodize/data/nyc/NYC - Neighborhood Tabulation Areas.kml
neighborhoodize/data/zillow/.DS_Store
neighborhoodize/data/zillow/ZillowNeighborhoods-IL/ZillowNeighborhoods-IL.dbf
neighborhoodize/data/zillow/ZillowNeighborhoods-IL/ZillowNeighborhoods-IL.prj
neighborhoodize/data/zillow/ZillowNeighborhoods-IL/ZillowNeighborhoods-IL.shp
neighborhoodize/data/zillow/ZillowNeighborhoods-IL/ZillowNeighborhoods-IL.shp.xml
neighborhoodize/data/zillow/ZillowNeighborhoods-IL/ZillowNeighborhoods-IL.shx
neighborhoodize/data/zillow/ZillowNeighborhoods-NY/ZillowNeighborhoods-NY.dbf
neighborhoodize/data/zillow/ZillowNeighborhoods-NY/ZillowNeighborhoods-NY.prj
neighborhoodize/data/zillow/ZillowNeighborhoods-NY/ZillowNeighborhoods-NY.shp
neighborhoodize/data/zillow/ZillowNeighborhoods-NY/ZillowNeighborhoods-NY.shp.xml
neighborhoodize/data/zillow/ZillowNeighborhoods-NY/ZillowNeighborhoods-NY.shx
Neighborhoodize-0.9.6.dist-info/LICENSE.md
Neighborhoodize-0.9.6.dist-info/METADATA
Neighborhoodize-0.9.6.dist-info/WHEEL
Neighborhoodize-0.9.6.dist-info/top_level.txt
Neighborhoodize-0.9.6.dist-info/RECORD
